dynamodb_stream_router/__init__.py
dynamodb_stream_router/exceptions.py
dynamodb_stream_router/record.py
dynamodb_stream_router/conditions/__init__.py
dynamodb_stream_router/conditions/lexer.py
dynamodb_stream_router/conditions/parser.py
dynamodb_stream_router-0.0.9.dist-info/LICENSE
dynamodb_stream_router-0.0.9.dist-info/METADATA
dynamodb_stream_router-0.0.9.dist-info/WHEEL
dynamodb_stream_router-0.0.9.dist-info/top_level.txt
dynamodb_stream_router-0.0.9.dist-info/RECORD
